{
   "entities" : {
      "FREIGHT_RATE" : null,
      "PORT" : null,
      "CHARTERER" : null,
      "ETA" : null,
      "CHARTER_TYPE" : null,
      "DISCHARGE_PORT" : null,
      "CONTACT" : null,
      "LAYCAN" : null,
      "OPEN_DATE" : null,
      "IMO" : null,
      "CARGO" : null,
      "VESSEL_TYPE" : null,
      "LOAD_PORT" : null,
      "DWT" : null,
      "VESSEL" : null
   },
   "text" : "\n\nThanks and Regards,\n\nMs. Eleanor Rodriguez\nOperations Executive\n\n\nSobha Sapphire Bldg. Office No. 906 Business Bay, P.O. Box 123175, Dubai United Arab Emirates\nTel: (+9714) 434 1628 l Fax: (+9714) 434 1629 l Mobile/Whatsapp: (+97150) 456 9584\nTeams: ⁠Transbulk5 \nWeChat: TransbulkOps_Eleanor\nEmail: operations@transbulk.ae | transblk@eim.ae \nWebsite: http://www.transbulk.ae\n\n-----Original Message-----\nFrom: postmaster <postmaster@emirates.net.ae> \nSent: Wednesday, 26 November 2025 11:04 AM\nTo: transblk@emirates.net.ae\nSubject: Returned mail: see transcript for details\n\nThe original message was received at Wed, 26 Nov 2025 11:00:15 +0400\nfrom:\n<transblk@eim.ae>\n\n   ----- The following addresses had permanent fatal errors ----- <ravindran@bancosta.com>\n    (reason: 550 5.1.1 <ravindran@bancosta.com>: Recipient address rejected: undeliverable address: Recipient address lookup failed) <chartering@raiseoncarriers.com>\n    (reason: 550 Host unknown)\n\n   ----- Transcript of session follows ----- ... while talking to mail4.bancosta.com.:\n>>> DATA\n<<< 550 5.1.1 <ravindran@bancosta.com>: Recipient address rejected: undeliverable address: Recipient address lookup failed\n550 5.1.1 <ravindran@bancosta.com>: Recipient address rejected: undeliverable address: Recipient address lookup failed <<< 421 4.7.0 mail.bancosta.it Error: too many errors\n550 5.0.0 Host unknown\n"
}
