{
   "text" : " \n \n \n \n \nBest Regards:\n \n\n \nMR. DEEPESH MAJIGAMKAR\nMob:- + 91 9730358718 (whatsapp) // +91 9156366155\nTeams/Skype:deepeshmajigamkar@hotmail.com\nEmail:  <mailto:chartering@varitasnavigation.com>\nchartering@varitasnavigation.com\nWebsite:- www.varitasnavigation.com\n \nFrom: Neos Shipping Inc <chartering@neosshipping.gr> \nSent: 26 November 2025 13:39\nTo: _ Neos Shipping Inc <chartering@neosshipping.gr>\nSubject: RE: MV KEA (REF:2507ENZ00) (REF:2507GH400)\n \nTELiX MSG: 07GH4-00 26/11/25 10:09 +02:00\n\n\nNEOS SHIPPING INC\n \n \n \n \n \nPLS PROPOSE FOR : \n \nOPEN  KRISHNAPATNAM OA 2-7 DECEMBER 2025 AGW WP UCE\n \n LAST CARGO : UREA IN BULK \n \nBOD : 1300-1350 VLSFO AND 165 - 175 LSMGO \n \n \nRIGHTSHIP SCORE 4/5 AND GHG B\n \n \nMV KEA SHORT DESCRIPTION\nABT 75.633 DWT ON ABT 14,20 M SSW - TPC 68.3\nBLT 2010 / MALTA FLAG /CLASS BV\nLOA/BEAM 225,00/32,26 M\n7 H/H\nABT 90.000 CBM GRAIN CAPACITY, INCL. HATCH COAMINGS\nSPEED (ALW ABT):  B/L: 12 AT 22 /24.5 MT+0,2 LSMGO\nECO: B/L: 11 AT 19/20  MT+0.2 LSMGO\nADA\n \nBest Regards\n \nBest regards\nDaniel Stergiou  \nSenior Chartering Executive\nNEOS SHIPPING INC\nEmail to: chartering@neosshipping.gr\nSkype: sterdmarine-daniel \nTel:   +30 210 8956114\nMob: +30 6975102474\nTeams:  <https://teams.live.com/l/invite/FEA28jzkUfFWkr-Sxg>\nhttps://teams.live.com/l/invite/FEA28jzkUfFWkr-Sxg\n <https://neosshipping.gr> https://neosshipping.gr\n(as brokers only)\n\n\n \nNEOS SHIPPING INC\nDRY CARGO CHARTERING\n\n\n \nNafsikas 9 ,1st Floor-Glyfada\nGreece\nPC 16675\n(AS BROKERS ONLY)\nDisclaimer Notice\nThe content of this email is confidential and intended for the recipient\nspecified in message only. It is strictly forbidden to share any part of\nthis message with any third party, without a written consent of the sender.\nIf you received this message by mistake, please reply to this message and\nfollow with its deletion, so that we can ensure such a mistake does not\noccur in the future.\n \n \n",
   "entities" : {
      "CARGO" : null,
      "DWT" : null,
      "VESSEL" : [
         "MV KEA SHORT DESCRIPTION"
      ],
      "LOAD_PORT" : null,
      "VESSEL_TYPE" : null,
      "DISCHARGE_PORT" : null,
      "CHARTER_TYPE" : null,
      "ETA" : null,
      "PORT" : [
         "KRISHNAPATNAM OA"
      ],
      "CHARTERER" : null,
      "FREIGHT_RATE" : null,
      "IMO" : null,
      "OPEN_DATE" : [
         "2-7 DECEMBER 2025"
      ],
      "LAYCAN" : null,
      "CONTACT" : null
   }
}
