{
   "entities" : {
      "DISCHARGE_PORT" : [
         "Shuaiba, Kuwait"
      ],
      "CHARTER_TYPE" : null,
      "ETA" : null,
      "PORT" : null,
      "CHARTERER" : [
         "VARITAS NAVIGATION"
      ],
      "FREIGHT_RATE" : null,
      "IMO" : null,
      "OPEN_DATE" : null,
      "LAYCAN" : [
         "15-20th December 2025"
      ],
      "CONTACT" : null,
      "CARGO" : [
         "SEMICOKE"
      ],
      "VESSEL" : null,
      "DWT" : null,
      "LOAD_PORT" : [
         "Tianjin, China"
      ],
      "VESSEL_TYPE" : null
   },
   "text" : " \n \n \n \n \nBest Regards:\n \n\n \nMR. DEEPESH MAJIGAMKAR\nMob:- + 91 9730358718 (whatsapp) // +91 9156366155\nTeams/Skype:deepeshmajigamkar@hotmail.com\nEmail:  <mailto:chartering@varitasnavigation.com>\nchartering@varitasnavigation.com\nWebsite:- www.varitasnavigation.com\n \nFrom: postmaster@marbrokers.com <postmaster@marbrokers.com> \nSent: 24 November 2025 10:26\nTo: chartering@varitasnavigation.com\nSubject: Undeliverable: ACC VARITAS NAVIGATION\n \nDelivery has failed to these recipients or groups:\n <mailto:aeilon@mbc-hellas.com> aeilon@mbc-hellas.com\nYour message couldn't be delivered. The Domain Name System (DNS) reported\nthat the recipient's domain does not exist.\nContact the recipient by some other means (by phone, for example) and ask\nthem to tell their email admin that it appears that their domain isn't\nproperly registered at their domain registrar. Give them the error details\nshown below. It's likely that the recipient's email admin is the only one\nwho can fix this problem.\nFor more information and tips to fix this issue see this article:\nhttps://go.microsoft.com/fwlink/?LinkId=389361.\n \n\n\n\n\n\n\nDiagnostic information for administrators:\nGenerating server: SA1PR19MB8952.namprd19.prod.outlook.com\naeilon@mbc-hellas.com\nRemote server returned '550 5.4.310 DNS domain mail.marbrokers.com does not\nexist [Message=InfoDomainNonexistent]\n[LastAttemptedServerName=mail.marbrokers.com]\n[DM2PEPF0000382A.namprd04.prod.outlook.com 2025-11-24T04:56:18.220Z\n08DE2995965FC100]'\nOriginal message headers:\nARC-Seal: i=1; a=rsa-sha256; s=arcselector10001; d=microsoft.com; cv=none;\n \nb=FBkW0VPSWMocWIaOEJx2PHi7vZAFY/2/XxghxxAfyiU+mBasSO18eom175AhrBLbZUHN/5aynL\n4cTcBNUzOUSGLfkTgS4vS/s6iU+5ngS3mnslstUzgMqM0EUt9e0tVbhra5Kc/Q/c/x6pCL1yp8ZG\nP8+UiPvn8IXvIrM82Y97usKLTkZYBygY28i+yMme6IuAIofssr4+SVeWOx9h25RGx3vDRGJTiS5v\njUtpNTBWKoJ/arVHzhgbMX65V8RyNpF7CCqrqpxVqR1TnHPUaS7wHXomTgNnDQxEwTfOPGNthaiT\nKxHNggSkrKVhLkd+kqrUIJQgHbjJ4/KglCvS6K3g==\nARC-Message-Signature: i=1; a=rsa-sha256; c=relaxed/relaxed;\nd=microsoft.com;\n s=arcselector10001;\n \nh=From:Date:Subject:Message-ID:Content-Type:MIME-Version:X-MS-Exchange-AntiS\npam-MessageData-ChunkCount:X-MS-Exchange-AntiSpam-MessageData-0:X-MS-Exchang\ne-AntiSpam-MessageData-1;\n bh=OXdEHpE/hD/5iUjEV/fuVwVNgAse4PLwU6pPadaQLkk=;\n \nb=HNPhJuX2OebHTbvP79o7l4p8lt6rmocGdYeSz2+0PGFUpNBRAP2lRHaY0zCec/MVr7QfVh4Ytv\nba00+EHljh2h3sSrwqqHN2DwA1YQnXJJV1CiMQ6q1a7oRd1xxxs/Z/2Sx1LCpTRDGL8l/CTpxG4E\ndBr9CjRIu13gHp88gh6dh0MY41Ce3j0kTZ80attfJYKMltYxQKoCqmrlZOMEwj5Dheh5AaKuAUS6\nz4sB6qdOIRGfbVFZR9G7X6r4droOF7QRiSlVy/HD5noiMfEH9aoW9Jmd7jEsjyc5I8RfwZPOzrvn\nGOEDVSUne0yiD4kTCN07rHrL4nnoRh8E4OvUPLLQ==\nARC-Authentication-Results: i=1; mx.microsoft.com 1; spf=pass (sender ip is\n 94.136.184.46) smtp.rcpttodomain=mbc-hellas.com\n smtp.mailfrom=varitasnavigation.com; dmarc=bestguesspass action=none\n header.from=varitasnavigation.com; dkim=fail (no key for signature)\n header.d=varitasnavigation.com; arc=none (0)\nReceived: from CH2PR19CA0012.namprd19.prod.outlook.com\n(2603:10b6:610:4d::22)\n by SA1PR19MB8952.namprd19.prod.outlook.com (2603:10b6:806:46a::15) with\n Microsoft SMTP Server (version=TLS1_2,\n cipher=TLS_ECDHE_RSA_WITH_AES_256_GCM_SHA384) id 15.20.9343.15; Mon, 24 Nov\n 2025 04:56:14 +0000\nReceived: from CH2PEPF0000009A.namprd02.prod.outlook.com\n (2603:10b6:610:4d:cafe::7d) by CH2PR19CA0012.outlook.office365.com\n (2603:10b6:610:4d::22) with Microsoft SMTP Server (version=TLS1_3,\n cipher=TLS_AES_256_GCM_SHA384) id 15.20.9343.17 via Frontend Transport;\nMon,\n 24 Nov 2025 04:56:06 +0000\nAuthentication-Results: spf=pass (sender IP is 94.136.184.46)\n smtp.mailfrom=varitasnavigation.com; dkim=fail (no key for signature)\n header.d=varitasnavigation.com;dmarc=bestguesspass action=none\n header.from=varitasnavigation.com;compauth=pass reason=109\nReceived-SPF: Pass (protection.outlook.com: domain of varitasnavigation.com\n designates 94.136.184.46 as permitted sender)\n receiver=protection.outlook.com; client-ip=94.136.184.46;\n helo=vmi2441136.contaboserver.net; pr=C\nReceived: from vmi2441136.contaboserver.net (94.136.184.46) by\n CH2PEPF0000009A.mail.protection.outlook.com (10.167.244.22) with Microsoft\n SMTP Server (version=TLS1_3, cipher=TLS_AES_256_GCM_SHA384) id 15.20.9366.7\n via Frontend Transport; Mon, 24 Nov 2025 04:56:13 +0000\nReceived: from LAPTOPP6RKI9ML (unknown [103.39.29.144])\n        by vmi2441136.contaboserver.net (Postfix) with ESMTPSA id\n8FB426A0937;\n        Mon, 24 Nov 2025 05:55:58 +0100 (CET)\nDKIM-Signature: v=1; a=rsa-sha256; c=relaxed/relaxed;\n        d=varitasnavigation.com; s=default; t=1763960167;\n        bh=A7PbDazuQxX76Yr4K4Rfd72/kcHJv+mcEM4D9A5XQLY=; h=From:Subject;\n  b=AitnkW4yeFU2zbV6hd76d20/zdScVRUJglpi4Rq4Xk9EztalsHmmqQ/xozYir/2u0\n         kljSrnDsyyf2hIzQZGnRmutRnWe9t11J82scodi0tEZ0OFYDpKUrEEkE4yvzWfM8qj\n         9lrz+DWNxum6KRkN3eWeeh7EekQnNmiSyJv1i2EO760O9RMunxRzdU9H6jjoJ3Z10f\n         sUSil5SgqsEynk9WW7TWKSslkwGHxqdTP3WR5cko0cGARpM0BMJ7l+6umlwNV8aE/j\n         +c7VzSc0u1bqt7f8O7WMYDY2U2F1+ony2DrqfQGQK6IqOX1AmKctvf0szh4C90SiVd\n         Yv3juWjxnP0Fw==\nAuthentication-Results-Original: vmi2441136.contaboserver.net;\nspf=pass\n (sender IP is 103.39.29.144) smtp.mailfrom=chartering@varitasnavigation.com\n smtp.helo=LAPTOPP6RKI9ML\nReceived-SPF: pass (vmi2441136.contaboserver.net: connection is\nauthenticated)\nFrom: <chartering@varitasnavigation.com>\nCC: 'Varitas Navigation' <chartering@varitasnavigation.com>,\n        \"chartering@mbc-hellas.com\" <chartering@mbc-hellas.com>\nSubject: ACC VARITAS NAVIGATION\nDate: Mon, 24 Nov 2025 10:25:56 +0530\nMessage-ID: <262101dc5cfe$a10ee9f0$e32cbdd0$@varitasnavigation.com>\nMIME-Version: 1.0\nContent-Type: multipart/related;\n        boundary=\"----=_NextPart_000_2622_01DC5D2C.BAC921C0\"\nX-Mailer: Microsoft Outlook 16.0\nThread-Index: Adxc/l/PbvsjcqezRGydD6lPQ7JR1Q==\nContent-Language: en-in\nReturn-Path: chartering@varitasnavigation.com\nX-EOPAttributedMessage: 0\nX-EOPTenantAttributedMessage: 981afe8b-0e04-4a09-a960-f0b7f5d8d26b:0\nX-MS-PublicTrafficType: Email\nX-MS-TrafficTypeDiagnostic: CH2PEPF0000009A:EE_|SA1PR19MB8952:EE_\nX-MS-Office365-Filtering-Correlation-Id:\n0dcdad85-d12e-4ba1-4c9c-08de2b15cb1c\nX-MS-Exchange-AtpMessageProperties: SA|SL\nX-LD-Processed: 981afe8b-0e04-4a09-a960-f0b7f5d8d26b,ExtAddr,ExtFwd\nX-Microsoft-Antispam:\nBCL:0;ARA:13230040|4053099003|13003099007|4076899003|8096899003;\nX-Microsoft-Antispam-Message-Info:\n=?us-ascii?Q?AptNJ30u1qJsc07jw8vDMs+2D/DtB5O3+ysagtzh7oEwjFAlfP/jZSYaTAr6?=\n =?us-ascii?Q?FsMaKPjGmOl4FUwY0n7ke2kJkH61b4G4hSSXJYFv97GJcaeV6444+RKS9Er+?=\n =?us-ascii?Q?9xnUw8z93wad0uQ+tiP2gb19anDje7X0nAcQaWOFgY0edlNtj0rp2FtQgZ3D?=\n =?us-ascii?Q?s7BaxY3DJAhYboDGsZL7VMxL0+c0bgGQrk6iXCX9o2YL4YdZa8p6TC9eCo08?=\n =?us-ascii?Q?demzw4k9+TCMT3uBI2zVuNFbx2kkIfqAVwnRgMKsTbx0Ipn4ptSGjykNtfYm?=\n =?us-ascii?Q?3yq71FikhKdIbUOB5cQxkGgqEyF5Lkl0M+Z2euvV9Z/QldW30btlQJVhzYcw?=\n =?us-ascii?Q?avn3v9uc5KlPkqHUiIiQ15TPxFnyWDnimLBGNIquPGjgAvWurSoSe4U+3/f+?=\n =?us-ascii?Q?UhKV5q85s0MiGLEhXJtTLo3tLyo5/uucZ+lbebK3YsYU0367aEwZjMUuRk4Q?=\n =?us-ascii?Q?7EZQWJAu6Yd/jsnOsS8tFgX29wER5wYESZhJkKn/3UhK2609S2wfkhPJmbxV?=\n =?us-ascii?Q?RoDIhSl2N0f/bF+Op9oGLbaksEB9M6tAWYu82N1x9IycXsiHREeylOh6H+z+?=\n =?us-ascii?Q?2UdD6eWzmPn19gv4wyBN7lbJC8zLCSf7v8lIF4yN6z8xjmU0BTOisnBllMNN?=\n =?us-ascii?Q?xZYrSIfxxZeLMAiP4jj5IvQyypGDkiYNuktWXY7ip/o5yixmP2AlaAwpSiTK?=\n =?us-ascii?Q?ddVbHiPGmU7Nn4rXGk6T2R4jricvjtdndvyN8mr5dlBCF7xTdeQidq/goJoX?=\n =?us-ascii?Q?76VNb8/FkgjsO1vsxeY9OcYrYQTrvn9VG0SSc8FZpxWsxHrB2C95pt7gKHsN?=\n =?us-ascii?Q?lwV0oRL6xrlBzvy17S66QzaRAMkwW2AkTk3WH4sBJkngJWsOeH0GDLNU420T?=\n =?us-ascii?Q?ko0cMQyg6eW8yFONq2TXEqPwbO/zpLBKuQZUsjIkjaz45ZqncYnulPNPdm8e?=\n =?us-ascii?Q?46ndztYwm0d1+SLTQSjMVdwgE9CsPMFn8SbkHxWBFF7N5//vV2kOwWeMuWVz?=\n =?us-ascii?Q?wGCRKRkzLY9uOvEdDAexQsFg7CQRqakNwAyz/AKfL/wWUzWYBKfSpeUVhtfI?=\n =?us-ascii?Q?8YNn0SaoVHUw+jRRcmdrT9oKwXbfh5PWrsr5LjEIKBT26t5iDIVoPuTrERYL?=\n =?us-ascii?Q?IN9eA4XH6TEzAqeMFWJg0b0qH40x+s6Ks26eVXX2LiS4pFIAqWXRfI8rB7PN?=\n =?us-ascii?Q?csAbsL9XKng6LxFYc3gHXzfDmboGH3iz/HWOJmYvgmGNW7RnWrxG3DpTtjW/?=\n =?us-ascii?Q?QL5NtXKbBYR/gC3R772FOu9TjvAAcMBC2x7M2rZo86k1348h2uc2GeN9lEUo?=\n =?us-ascii?Q?Mb98i0JN6qU4PdN6NLlC5VKvZbKNf8JfFjlZiPJ6izGObJ/K+DoZp6/eVfH9?=\n =?us-ascii?Q?SNPwjknrrzH0HbU4pc80CvK7iNJH9twOlxApCVdNn0JVZKMb2bdJGgLTbSk2?=\n =?us-ascii?Q?xgwFq4ohCirgZ/c3LUOFr7HMw8aEqNgQJRsRxUsYz7j+0IQN5ENMsqurHhJV?=\n =?us-ascii?Q?W6T0jvefUj0JRKT+VVH8XIF1B0u62GhTpNjj1bi64RJYxYmA4SjbnOwx3V3t?=\n =?us-ascii?Q?anHYnmCbs3CPiG54lUNBYQLvVXTN1hEVW/xU+gjtGjLvi8odx4Rb9LxMBvga?=\n =?us-ascii?Q?fgC27HplmLIbAhZLso43ZDPkT4dl3yJBINQrSjamtcW6czMq3OjUoiQPzWm4?=\n =?us-ascii?Q?wGATk3tnl0uKF6G6YKNobFp3dxWjdhW9moRUC16PIYz52+kAaJxAzdKXKgHD?=\n =?us-ascii?Q?kZ/6kLyq+0g7LRcFZEsgR/VOCArC3LUfDFRFeOWJV20KU1sBZny16T8VAWBu?=\n =?us-ascii?Q?vH8eWBcbwLdxU61/hFiUr2jCQgIaq9qxU1NrhKXR2Fp4kLyTdNybhp4CU9/g?=\n =?us-ascii?Q?ybKEtdomY7NPI0qRAhuDc11FxiCUQzmh64P+GpZfS8wrqbFRsx3S4+QSl3p8?=\n =?us-ascii?Q?Ur2A7G+qcqCx7OX+npW9iKqhdCUlgmJ9yVFaM2poqpASyJDch/5+HYl8vG6U?=\n =?us-ascii?Q?FGREtCuJUC792YjMDSF6jM9dYnXUECxNysK0q11eLKTDBbF1qt1lArTIWuEv?=\n =?us-ascii?Q?R+mN2qb9NyD+Vakf6DiPbsA0IeeU2BBnOfNd6k/BkXI0/hAWvLte6Is6oI80?=\n =?us-ascii?Q?QS0x6pqlbv1SJkOoXFkYUHXVRWZDUE2Cl4OEVsfFyduWEx60c/xY0H4wjLKm?=\n =?us-ascii?Q?pDnDIX9Fo1aIycjiFnN52sgQKGDHIJhcSTwIi2qE0Werx0oeElvJvQTqpAbJ?=\n =?us-ascii?Q?xcuyFBnnjYfKp2uN8P0m3YjGX0dB9PKFTFX+/j2Fs0Ykb+dE7pLmMaqnniYx?=\n =?us-ascii?Q?VR2go6u0zDVvMba3Mijw2+uz8nDRzEz1bqVy6lp0H6tgcKavEqJMIW0513ZZ?=\n =?us-ascii?Q?XQ6zqkqet70mrEml9RwSE3zLhk3KpbQGmsROid8gX2gH4MppgchT/KS9ac8U?=\n =?us-ascii?Q?i4q9+YIok8Jsg5AvnkGaJPn2Tbvk2XJits7VjNmSDk3ZNyFHn4ZGmTextre7?=\n =?us-ascii?Q?r1P8b+/r8Ha2OPSNL7+W2jPjBRU0hO8n0Kx4Fg3YPdHgOuhC7RKXuYNu39A7?=\n =?us-ascii?Q?bUQQ4xL4wlyfWOmw19brRhbJv19SUjLGC1QSoYXfyqSUZnf1FkEXlvYbfUgU?=\n =?us-ascii?Q?DA=3D=3D?=\nX-Forefront-Antispam-Report:\nCIP:94.136.184.46;CTRY:IN;LANG:en;SCL:1;SRV:;IPV:NLI;SFV:NSPM;H:vmi2441136.c\nontaboserver.net;PTR:vmi2441136.contaboserver.net;CAT:NONE;SFS:(13230040)(40\n53099003)(13003099007)(4076899003)(8096899003);DIR:INB;\nX-Auto-Response-Suppress: DR, OOF, AutoReply\nX-OriginatorOrg: marbrokers.com\nX-MS-Exchange-CrossTenant-OriginalArrivalTime: 24 Nov 2025 04:56:13.0542\n (UTC)\nX-MS-Exchange-CrossTenant-Network-Message-Id:\n0dcdad85-d12e-4ba1-4c9c-08de2b15cb1c\nX-MS-Exchange-CrossTenant-Id: 981afe8b-0e04-4a09-a960-f0b7f5d8d26b\nX-MS-Exchange-CrossTenant-AuthSource:\nCH2PEPF0000009A.namprd02.prod.outlook.com\nX-MS-Exchange-CrossTenant-AuthAs: Anonymous\nX-MS-Exchange-CrossTenant-FromEntityHeader: Internet\nX-MS-Exchange-Transport-CrossTenantHeadersStamped: SA1PR19MB8952\nX-OrganizationHeadersPreserved: SA1PR19MB8952.namprd19.prod.outlook.com\nX-CrossPremisesHeadersFilteredByDsnGenerator:\n        SA1PR19MB8952.namprd19.prod.outlook.com\nDear All,\n\nGood day.\n\n \n\n// FULLY FIRM // \n\n \n\nACC VARITAS NAVIGATION\n\n3000 mt +/- 10% MOLOO semicoke in jumbo bags SF 1.8-2.0.\n\nBag Size: 1.2X1.2X1.24 m, u/w 0.95 -1 tons. \n\nLoad port: Tianjin, China\n\nDischarge port: Shuaiba, Kuwait.\n\nLoad rate: CQD \n\nDischarge: Liner out.\n\nLaycan 15-20th December 2025.\n\nAs part cargo.\n\n2.5% Addcom\n\n \n\n \n\nBest Regards:\n\n \n\n\n\n \n\nMR. DEEPESH MAJIGAMKAR\n\nMob:- + 91 9730358718 (whatsapp) // +91 9156366155\n\nTeams/Skype:deepeshmajigamkar@hotmail.com\n\nEmail:  <mailto:chartering@varitasnavigation.com>\nchartering@varitasnavigation.com\n\nWebsite:- www.varitasnavigation.com\n\n \n\n"
}
