[
  {
    "email_type": "Tonnage",
    "vessel_name": "TRIUMPH OCEAN DWCC 13000 MUNDRA 21 JAN",
    "vessel_type": "Bulk Carrier",
    "dwt": "32379",
    "built_year": "",
    "flag": "",
    "imo": "",
    "grt": "",
    "nrt": "",
    "loa": "",
    "beam": "",
    "grain_capacity": "",
    "open_port": "Tuticorin, India",
    "open_date": "2026-02-03",
    "close_date": "2026-02-08",
    "matching_region": "World Wide",
    "restrictions": [],
    "confidence_score": 0.87
  },
  {
    "email_type": "Tonnage",
    "vessel_name": "YONG SHENG 151 DWCC 11600 PARADIP 23 JAN ON SUB",
    "vessel_type": "Bulk Carrier",
    "dwt": "12005",
    "built_year": "2012",
    "flag": "",
    "imo": "",
    "grt": "",
    "nrt": "",
    "loa": "",
    "beam": "",
    "grain_capacity": "",
    "open_port": "MONGLA",
    "open_date": "2026-01-20",
    "close_date": "2026-01-25",
    "matching_region": "Ukraine",
    "restrictions": [],
    "confidence_score": 0.92
  },
  {
    "email_type": "Tonnage",
    "vessel_name": "VAST OCEAN 7 DWCC 13000 MUNDRA 23 JAN",
    "vessel_type": "Bulk Carrier",
    "dwt": "68028",
    "built_year": "",
    "flag": "",
    "imo": "",
    "grt": "",
    "nrt": "",
    "loa": "",
    "beam": "",
    "grain_capacity": "",
    "open_port": "Chittagong, Bangladesh",
    "open_date": "",
    "close_date": "",
    "matching_region": "Bangladesh",
    "restrictions": [],
    "confidence_score": 0.79
  },
  {
    "email_type": "Tonnage",
    "vessel_name": "CS CRYSTAL",
    "vessel_type": "Bulk Carrier",
    "dwt": "35244",
    "built_year": "2003",
    "flag": "MARSHALL ISLANDS",
    "imo": "",
    "grt": "1860",
    "nrt": "32379",
    "loa": "119.99m",
    "beam": "132.53m",
    "grain_capacity": "98740",
    "open_port": "",
    "open_date": "",
    "close_date": "",
    "matching_region": "Vietnam",
    "restrictions": [
      "NO ADVERSE CURRENT AND NO\n\nNEGATIVE INFLUENCE OF SWELL",
      "NO GRAB\n\nSPEED"
    ],
    "confidence_score": 0.81
  }
]