[
  {
    "email_type": "Tonnage",
    "vessel_name": "CANADIAN BULKER",
    "vessel_type": "Bulk Carrier",
    "dwt": "39000",
    "built_year": "2019",
    "flag": "",
    "imo": "",
    "grt": "",
    "nrt": "",
    "loa": "",
    "beam": "",
    "grain_capacity": "",
    "open_port": "KUWAIT",
    "open_date": "2026-12-08",
    "close_date": "2026-12-13",
    "matching_region": "Persian Gulf",
    "restrictions": [],
    "confidence_score": 0.92
  },
  {
    "email_type": "Tonnage",
    "vessel_name": "CANADIAN BULKER",
    "vessel_type": "Bulk Carrier",
    "dwt": "",
    "built_year": "2019",
    "flag": "",
    "imo": "9855422",
    "grt": "",
    "nrt": "",
    "loa": "179.9m",
    "beam": "30m",
    "grain_capacity": "",
    "open_port": "",
    "open_date": "",
    "close_date": "",
    "matching_region": "",
    "restrictions": [],
    "confidence_score": 0.75
  }
]