[
  {
    "email_type": "Tonnage",
    "vessel_name": "BAO RI LING",
    "vessel_type": "Bulk Carrier",
    "dwt": "",
    "built_year": "",
    "flag": "",
    "imo": "",
    "grt": "",
    "nrt": "",
    "loa": "",
    "beam": "",
    "grain_capacity": "",
    "open_port": "CJK,",
    "open_date": "2025-12-25",
    "close_date": "2025-12-30",
    "matching_region": "China",
    "restrictions": [],
    "confidence_score": 0.75
  },
  {
    "email_type": "Tonnage",
    "vessel_name": "BAO REN LING",
    "vessel_type": "Bulk Carrier",
    "dwt": "",
    "built_year": "",
    "flag": "",
    "imo": "",
    "grt": "",
    "nrt": "",
    "loa": "",
    "beam": "",
    "grain_capacity": "",
    "open_port": "KCS,",
    "open_date": "2025-12-25",
    "close_date": "2025-12-30",
    "matching_region": "Thailand",
    "restrictions": [],
    "confidence_score": 0.75
  },
  {
    "email_type": "Tonnage",
    "vessel_name": "BAO NING LING",
    "vessel_type": "Bulk Carrier",
    "dwt": "",
    "built_year": "",
    "flag": "",
    "imo": "",
    "grt": "",
    "nrt": "",
    "loa": "",
    "beam": "",
    "grain_capacity": "",
    "open_port": "SEMARANG,",
    "open_date": "2025-12-22",
    "close_date": "2025-12-27",
    "matching_region": "",
    "restrictions": [],
    "confidence_score": 0.73
  },
  {
    "email_type": "Tonnage",
    "vessel_name": "YIN HUA 1",
    "vessel_type": "Bulk Carrier",
    "dwt": "",
    "built_year": "",
    "flag": "",
    "imo": "",
    "grt": "",
    "nrt": "",
    "loa": "",
    "beam": "",
    "grain_capacity": "",
    "open_port": "surabaya,",
    "open_date": "2025-12-26",
    "close_date": "2025-12-31",
    "matching_region": "",
    "restrictions": [],
    "confidence_score": 0.73
  },
  {
    "email_type": "Tonnage",
    "vessel_name": "sheng cheng hai",
    "vessel_type": "Bulk Carrier",
    "dwt": "",
    "built_year": "",
    "flag": "",
    "imo": "",
    "grt": "",
    "nrt": "",
    "loa": "",
    "beam": "",
    "grain_capacity": "",
    "open_port": "jakarta,",
    "open_date": "2025-12-27",
    "close_date": "2026-01-01",
    "matching_region": "",
    "restrictions": [],
    "confidence_score": 0.73
  },
  {
    "email_type": "Tonnage",
    "vessel_name": "COS PROSPERITY",
    "vessel_type": "Bulk Carrier",
    "dwt": "",
    "built_year": "",
    "flag": "",
    "imo": "",
    "grt": "",
    "nrt": "",
    "loa": "",
    "beam": "",
    "grain_capacity": "",
    "open_port": "Colombo, Sri Lanka",
    "open_date": "2025-12-24",
    "close_date": "2025-12-29",
    "matching_region": "",
    "restrictions": [],
    "confidence_score": 0.73
  },
  {
    "email_type": "Tonnage",
    "vessel_name": "KANG SHUN",
    "vessel_type": "Bulk Carrier",
    "dwt": "",
    "built_year": "",
    "flag": "",
    "imo": "",
    "grt": "",
    "nrt": "",
    "loa": "",
    "beam": "",
    "grain_capacity": "",
    "open_port": "DAHEJ,",
    "open_date": "2025-12-21",
    "close_date": "2025-12-26",
    "matching_region": "West Coast India",
    "restrictions": [],
    "confidence_score": 0.75
  },
  {
    "email_type": "Tonnage",
    "vessel_name": "sheng ping hai",
    "vessel_type": "Bulk Carrier",
    "dwt": "",
    "built_year": "",
    "flag": "",
    "imo": "",
    "grt": "",
    "nrt": "",
    "loa": "",
    "beam": "",
    "grain_capacity": "",
    "open_port": "mombasa,",
    "open_date": "2026-01-05",
    "close_date": "2026-01-10",
    "matching_region": "",
    "restrictions": [],
    "confidence_score": 0.73
  },
  {
    "email_type": "Tonnage",
    "vessel_name": "BAO RI LING",
    "vessel_type": "Bulk Carrier",
    "dwt": "47829",
    "built_year": "2013",
    "flag": "CHINA",
    "imo": "",
    "grt": "16289",
    "nrt": "",
    "loa": "189.9m",
    "beam": "32.26m",
    "grain_capacity": "",
    "open_port": "",
    "open_date": "",
    "close_date": "",
    "matching_region": "China",
    "restrictions": [
      "NO ADVERSE CURRENT\n\nAND NO NEGATIVE INFLUENCE OF SWELL",
      "NO CIRCUMSTANCES ALLOWED"
    ],
    "confidence_score": 0.81
  },
  {
    "email_type": "Tonnage",
    "vessel_name": "BAO REN LING",
    "vessel_type": "Bulk Carrier",
    "dwt": "47761",
    "built_year": "2015",
    "flag": "CHINA",
    "imo": "",
    "grt": "16289",
    "nrt": "",
    "loa": "189.9m",
    "beam": "32.26m",
    "grain_capacity": "",
    "open_port": "",
    "open_date": "",
    "close_date": "",
    "matching_region": "China",
    "restrictions": [
      "NO ADVERSE CURRENT AND NO NEGATIVE INFLUENCE OF SWELL",
      "NO CIRCUMSTANCES ALLOWED"
    ],
    "confidence_score": 0.81
  },
  {
    "email_type": "Tonnage",
    "vessel_name": "YIN HUA 1",
    "vessel_type": "Standard Dry Bulk Carrier",
    "dwt": "46613",
    "built_year": "2013",
    "flag": "SDBC",
    "imo": "9673501",
    "grt": "",
    "nrt": "29232",
    "loa": "",
    "beam": "189.99m",
    "grain_capacity": "",
    "open_port": "",
    "open_date": "",
    "close_date": "",
    "matching_region": "China",
    "restrictions": [
      "NO ADVERSE CURRENT AND NO NEGATIVE INFLUENCE OF SWELL",
      "NO CIRCUMSTANCES ALLOWED"
    ],
    "confidence_score": 0.86
  },
  {
    "email_type": "Tonnage",
    "vessel_name": "SHENG CHENG HAI",
    "vessel_type": "Standard Dry Bulk Carrier",
    "dwt": "",
    "built_year": "2013",
    "flag": "",
    "imo": "",
    "grt": "32976",
    "nrt": "191425",
    "loa": "189.99m",
    "beam": "",
    "grain_capacity": "",
    "open_port": "",
    "open_date": "",
    "close_date": "",
    "matching_region": "South East Asia",
    "restrictions": [
      "NO ADVERSE CURRENT AND NO NEGATIVE INFLUENCE OF SWELL",
      "NO CIRCUMSTANCES ALLOWED"
    ],
    "confidence_score": 0.69
  },
  {
    "email_type": "Tonnage",
    "vessel_name": "BAO NING LING",
    "vessel_type": "Bulk Carrier",
    "dwt": "46094",
    "built_year": "",
    "flag": "CHINA PRC",
    "imo": "9604299",
    "grt": "16289",
    "nrt": "2969180",
    "loa": "189.9m",
    "beam": "32.26m",
    "grain_capacity": "606195",
    "open_port": "",
    "open_date": "",
    "close_date": "",
    "matching_region": "China",
    "restrictions": [
      "NO ADVERSE CURRENT AND NO NEGATIVE INFLUENCE OF SWELL",
      "NO CIRCUMSTANCES ALLOWED"
    ],
    "confidence_score": 0.88
  },
  {
    "email_type": "Tonnage",
    "vessel_name": "ON DRAFT OF 12.5 M SSW TPC 56.4",
    "vessel_type": "Bulk Carrier",
    "dwt": "55550",
    "built_year": "2006",
    "flag": "",
    "imo": "",
    "grt": "",
    "nrt": "30953",
    "loa": "",
    "beam": "189.9m",
    "grain_capacity": "",
    "open_port": "",
    "open_date": "",
    "close_date": "",
    "matching_region": "South East Asia",
    "restrictions": [
      "NO ADVERSE\n\nCURRENT AND NO NEGATIVE INFLUENCE OF SWELL",
      "NO CLAIMS WHATSOEVER MAY BE\n\nBROUGHT FOR UNDERPERFORMANCE"
    ],
    "confidence_score": 0.74
  },
  {
    "email_type": "Tonnage",
    "vessel_name": "",
    "vessel_type": "Standard Dry Bulk Carrier",
    "dwt": "",
    "built_year": "",
    "flag": "",
    "imo": "",
    "grt": "28780",
    "nrt": "162895",
    "loa": "189.9m",
    "beam": "",
    "grain_capacity": "",
    "open_port": "",
    "open_date": "",
    "close_date": "",
    "matching_region": "South East Asia",
    "restrictions": [
      "NO ADVERSE CURRENT AND NO NEGATIVE INFLUENCE OF SWELL"
    ],
    "confidence_score": 0.49
  }
]