{
  "text": "Best Regards:\nMR. DEEPESH MAJIGAMKAR\nMob:- + 91 9730358718 (whatsapp) // +91 9156366155\nTeams/Skype:deepeshmajigamkar@hotmail.com\nEmail:\nchartering@varitasnavigation.com\nWebsite:-\nwww.varitasnavigation.com\nFrom:\nI N D O S I N O - SINCE 2000 - Professional Dry Bulk Shipbroking Company <chartering@rawatindosinogroup.co.in>\nSent:\n30 December 2025 11:39\nTo:\nrawatindosinogroup@gmail.com\nSubject:\n3S ANY FIRM OR BOOKED BIZ FOR BELOW DIRECT OWNER\\'S VESSEL OPEN SOUTH EAST ASIA AND FAR EAST\nI\nNDO SINO\n–\nS\nince 2000\nGOOD DAY FROM INDO SINO!\nPlease regularly update yr firm or booked order at our below email id.\nD I R E C T    T O N N A G E                (WE ARE HERE (24X7) FOR ALL OUR CLOSE FRIEND/SUPPORTING OWNER/CHARTERER/OPERATOR & BROKER ETC ETC\nWHAT CAN YOU PROPOSE FOR BELOW VERY VERY CLOSE LADY – NAME AND RATED BIZ WILL BE HIGHLY APPRECIATED\n–\nalways put vsl name in subject.\nWHO WANT TO FIX WITH US BEFORE NEW YEAR 2026\nMV VSM STAR\n7229 DWT             OPEN TAICHUNG 11 JAN 2026\n(VOY, TCT, TC Okay – Prefer S.e.a direction)\nMV\nVSM STAR\nSDBC,\nBox type\nCLASS/CCS\nFLAG/PAN\nBUILT/2011\nDWT/DWCC 7229/6700\nGRT/NRT 5092/2777\nL/B/D 112.80/17.20/9.10\nDRAFT/6.9\n3H/3H, HATCH SIZE: NO.1&2&3 17.68*11.2\n(\nHOLD CAPA: NO.1 3064.14, NO.2 3391.47, NO.3\n2938.30,TOTAL:9393.91\n)\nHYDRAULIC FOLDING HATCH\n2 CRANES x 15MTS\nSWL\n= ADA WOG=\nMV HTP AMBER\n(10,000MT)           OPEN ZAMBOANGA 28-31/JAN 2026\nTYPE OF SHIP: M. GENERAL CARGO\nTWIN DECK/ BUILT YEAR 2006\nNK CLASS / FLAG: PANAMA\nLOA/BREATH/DEPTH/ S. DRAFT: 108.22/19.60/13.3M / 8.48M\nGRT/NRT/ DWT/TPC 7,156/3,131/ 10,309.36 /17.84MT\nGRAIN/ BALE: 14,586.83/13,291.98 CBM\n2 HOLDS / 2 HATCHES HATCH SIZE: NO.1 24.5*14.0 NO.2 27.3*14.0\nCRANES: 2 X 30MT; COMBINABLE 60T\nPLEASED TO HEAR NAME AND RATED BIZ.\nBEST REGARDS // SHRISTI FOR MR LAKSHMAN SINGH RAWAT\nAs Shipbroker Only\nIndo Sino Chartering Agency Services – New  Delhi – India – Since 2000\nContact Details\nTEL\n: 00-91-11-49990590\nWhatsapp & Microsoft  Team\n: 00-91-9810827498 –\nindosinogroup@gmail.com\n/ indosino1\nhttps://teams.live.com/l/invite/FEAQvq5neOW40l0SQ4\nMOBILE\n: 00-91-9810827498 & 8447121555\nEMAIL\n:\nchartering@rawatindosinogroup.co.in\n&\nchartering@indosinogroup.com\n(For very ugent message or Negotiation always cc or bcc at\nindosinogroup@gmail.com\n)\nrawatindosinogroup.co.in\nemail powered by Google, setup by\nWeSetup.in",
  "entities": {
    "VESSEL": "MV VSM STAR\n7229 DWT             OPEN TAICHUNG 11 JAN 2026",
    "DWT": "7229",
    "PORT": "SOUTH EAST ASIA AND FAR EAST\nI\nNDO SINO",
    "CONTACT": "deepeshmajigamkar@hotmail.com",
    "EMAIL": "deepeshmajigamkar@hotmail.com",
    "PHONE": "91 9730358718 ",
    "OPEN_PORT": "SOUTH EAST ASIA AND FAR EAST\nI\nNDO SINO",
    "CARGO": "GRAIN",
    "CARGO_TYPE": "Dry Bulk",
    "TONNAGE_TYPE": "General Cargo",
    "EMAIL_TYPE": "TONNAGE",
    "MIN_SIZE": "1555",
    "MAX_SIZE": "981082",
    "BROKER": "MR. DEEPESH MAJIGAMKAR",
    "REGION": "FAR EAST",
    "MATCHING_REGION": "FAR EAST"
  }
}