{
  "text": "Best Regards:\nMR. DEEPESH MAJIGAMKAR\nMob:- + 91 9730358718 (whatsapp) // +91 9156366155\nTeams/Skype:deepeshmajigamkar@hotmail.com\nEmail:\nchartering@varitasnavigation.com\nWebsite:-\nwww.varitasnavigation.com\nFrom:\nMary Fatima Duhina <mary@seaspeedmarine.com>\nSent:\n10 December 2025 10:56\nSubject:\nMV FULMAR S /2010 BLT/ SDWT 79,403 MTS - OPEN @ INDONESIA ON 24/28 DEC\nDEAR SIR,\nGOOD DAY!\nKINDLY PLS PPS FOR ANY SUITABLE BIZ FOR THE BELOW VSL\n=========================================\n-\nMV FULMAR S\n/2010 BLT/\nSDWT 79,403 MTS - OPEN @ INDONESIA\nON\n24/28 DEC\nMV FULMAR S  === SDWT 79,403 MTS ===\nBUILT : 2010 DWT: 79403 MTS\nLOA : 229 MTRS / LBP:222 MTRS / BREADTH: 32,26 MTRS\nDRFT: 14,620 MTRS / DEPTH MLD: 20,25MTRS / TPC: 70,30 T\nCLASS : LLOYDS / FLAG: MARSALL ISLAND\nGEARLESS BC NEW PANAMA CANAL FITTED\nGRTE:43717 MTS NRT:26510 MTS\nHATCH AND HOLD DIMENTIONS\nHATCH AND HOLDS 7 HA SIDE-ROLLING TYPE / 7HO\nH1: 13,050*13,020 / H2-6: 18,270*15,00 / H7: 16,660*15,00\nGRAIN CAPACITY: 3,319,984 CBFT\nHOLD1: 350.286,50 CBFT   /  HOLD2: 535.618,05 CBFT   /   HOLD3: 488.049,15 CBFT\nHOLD4: 488.296,35 CBFT   /  HOLD5: 488.684,81 CBFT   /   HOLD6: 536.006,51 CBFT\nHOLD7: 432.922,90 CBFT\nCO2 IN HOLDS NOT FITTED, NO CARGO LOADING ON HATCH COVERS OR ON DECK\nALL ABT IN GOOD FAITH BUT WOG\nPLSD TO HEAR!\nBest Regards,\nMary Fatima Duhina\nChartering Executive\nSeaspeed Marine Management LLC\n1104, Mohammed Al Mulla Tower, Al Ittihad Road, P.O.Box 32658, Sharjah, U.A.E.\nTel :\n+971 6 5638938 | Fax : +971 6 5638939\nEmail:\ndry@seaspeedmarine.com\n|\nmary@seaspeedmarine.com\nTeams ID\n:\nhttps://teams.live.com/l/invite/FEAcsGvdoh-MRVgnQQ\nWechat ID & Whatsapp :\n+971 50 860 7046\nWebsite\n:\nwww.seaspeedmarine.com\nAs Brokers Only\nNote:\nSeaspeed Marine Management LLC will be migrating to our new email domain of\nseaspeedmarine.com\nfrom 1\nst\nFeb 2025.\nAll email addresses will change from:\n@cspeed.ae\nto\n@seaspeedmarine.com\n.\nRequest you to kindly update your address book to reflect the same.\nNote:\nSeaspeed Marine Management LLC will be migrating to our new email address,\ndry@seaspeedmarine.com\nfrom 1\nst\nFeb 2025. Request you to kindly update your address book to reflect the same and prevent any loss of communication.",
  "entities": {
    "VESSEL": "MV FULMAR S",
    "DWT": "79403",
    "CONTACT": "deepeshmajigamkar@hotmail.com",
    "EMAIL_TYPE": "TONNAGE",
    "OPEN_PORT": "Indonesia",
    "OPEN_DATE": "2025-12-24",
    "CLOSE_DATE": "2025-12-28",
    "TONNAGE_TYPE": "Bulk Carrier",
    "BROKER": "Volkan Gerez",
    "EMAIL": "chartering@turship.net",
    "PHONE": "+90-542-484 4025",
    "CARGO": "GRAIN",
    "CARGO_TYPE": "Dry Bulk",
    "MIN_SIZE": "1104",
    "MAX_SIZE": "973035"
  }
}