{
  "text": "Best Regards:\nMR. DEEPESH MAJIGAMKAR\nMob:- + 91 9730358718 (whatsapp) // +91 9156366155\nTeams/Skype:deepeshmajigamkar@hotmail.com\nEmail:\nchartering@varitasnavigation.com\nWebsite:-\nwww.varitasnavigation.com\nFrom:\nLEMA Chartering <chart@lemafcc.com>\nSent:\n07 January 2026 20:29\nSubject:\nTCT & period\n5 % ttl here incl 3.75 add comm\nCANFORNAV\n22/35,000 DWT\nDELY PORT ARTHUR\nREDELY SEVEN ISLANDS, CANADA\nSPOT - JAN 12\nTCT WITH CALCINED PETCOKE ABT 25 DAYS WOG\n+\nGujarathi\nSMX - UMX\nGEARS AND GRABS IMPERATIVE\nDELIVERY - PG / WCI RANGE\n15TH JAN ONWARDS\n1 TCT WITH 25 - 30 DAYS WOG\nREDEL - PG JAPAN RANGE\nCAN TRY 2 -3 LL AGAINST RIGHT CANDIDATE\n+\nGujarathi\n35-40 K DWT\n1ST WEEK OF FEB\nDELIVERY - ECI\nREDEL - WEST AFRICA\n1 TCT WITH BAGGED RICE TO WAFR VIA ECI\n+\nGujarathi\n30K - 38K DWT\nDURATION 6 + 6 MONTHS\nLESS THAN 15 YEARS OLD\nDEL: WW\nREDEL: WW\nWW TRADING WITH NORMAL EXCLUSIONS\n20 - 30 JAN\n+\nGujarathi\nSUPRA-ULTRA MAX 19 YEARS\nABT 6/8 MOS PERIOD TRY LONGER\nMID JAN\nDELY SPORE - JAPAN RGE\nREDELIVERY WW\nPREFER GOA TRADER\n+\nMAXIMA\n32/40000 DWT\nDELY PLATE\n8/20 JAN\nTRIP TO W.AFRICA (NO HRA)\nBULK GRAINS\n+\nMAXIMA\n28/38000 DWT\nDELY SINGAPORE-CJK RANGE\nJAN\nSHORT PERIOD 3/6 MON (CAN TRY LONGER)\nREDEL WW (CAN BE FLEXIBLE)\n+\nBULK ASIA\nMIN 33K DWT MAX TILL SMX\nWCI TO MED-BLACK SEA RANGE\nHARMLESS BULK / STEELS\nVIA GOA\n17 JAN ONWARDS\n30-35 DAYS WOG\n+\nAUTHENTIC\nLARGE SUPRA/PREF ULTRA\nDELY: CJK-JPN RGE\nMID-END JAN ONW\nPERIOD: UP TO 1 YEAR, FLAT RATE\nFLEXIBLE CP, WAFR HRA IMPERATIVE\n+\nALLIANZ\nSUPRA-UMX\n14/20 JAN\nDELY EC INDIA-CHITTAGONG\n1 TCT WITH IRON ORE FINES IN BULK VIA EC INDIA\nDURATION 25/27 DAYS WOG\nREDELY CHINA\n+\nALLIANZ\n1 TCT WITH BULK HARMLESS SLAG IN BULK\nSMAX / UMAX\nDELY N.CHINA\nREDELY INDIA / BDESH  RANGE\nDURATION 20-25 DAYS WOG\nLAYCAN 20TH JANUARY- 30TH JANUARY\n+\nALLIANZ BULK\n1 TCT WITH BULK HARMLESS COAL IN BULK\nSMAX / UMAX\nDELY E. KALI RANGE / S.KALI\nREDELY INDIA / BDESH  RANGE\nDURATION 20-25 DAYS WOG\n20- 30 JANUARY\n+\nNeoBulk\nSmax/ Ultra\n1 TCT with limestone/aggregates in bulk\nDely PG\nRedel Bangladesh\nDur Abt 20-25 days wog\n8-15 Jan (Try vsl dates)\n+\nMultimax\nSupra\n1 Tct with Harmless bulk\nDel Wci\n10-15 Jan\nRedl China\nDuration  30D Wog\n+\nMultimax\nSupra\n1 Tct with fertz\nDel Red Sea\nLaycan Spot or 10-15 Jan\nRedl India/China\nDuration  30-35D Wog\n+\nSEAWIND\nSMAX/UMAX\n17 JAN ONWARD\nDELY: S.E.A / SOUTH CHINA RANGE\nRE-DELY: W.AFR PICO (NON HRA)\n1TCT WITH H\\'LESS BAGS\nDURATION: ABT 65-70 DAYS WOG\n+\nGRAIN COMPASS\nSUPRA/ULTRA\nDEL WCI\n10-15 JAN\nDUR ABT 28-30 DAYS WOG\nREDEL 1 SP SING/JAPAN RANGE\nSUB DETAILS\n+\nAVENIR\nPMX/KMX\n1 TCT WITH HMLESS BULK\nDTM ECI\nREDEL WCI-KRISHNAPATNAM\n10-15 JAN\n+\nAVENIR\nSMX/UMX\nDTM VIETNAM\nREDEL BDESH\n1 TCT W CLINKER ( TRY 2-3LL )\nDURATION ABT 25-30 DAYS WOG\n14-18 JAN\n+\nAVENIR\nSMX/UMX\n1 TCT COAL\nDELY MEULABOH\nREDELY WCI\n17-26 JAN\n+\nHANSON\nHANDYSIZE(24K/40K DWT)\n1 TCT VIA BALTIC(NO RUSSIAN INVOLVEMENT)\nBULK GRAINS ABT 50 DAYS WOG\nDELY CONTI/SKAW/BALTIC\nREDELY PG/WCI VIA SUEZ\n18 JAN ONW(TRY TICK EARLIER/LATER)\nSergey Slepchenko\n-Chartering manager-\nchart@lemafcc.com\n+38-067-6211603\nmariupolshipbroker\nP\nart of Deniam Group AG\n2C Grangegorman Lower Smithfield, Dublin, Ireland",
  "entities": {
    "DWT": "35,000",
    "LAYCAN": "30-35 DAY",
    "CONTACT": "deepeshmajigamkar@hotmail.com",
    "EMAIL": "deepeshmajigamkar@hotmail.com",
    "PHONE": "91 9730358718 ",
    "CARGO": "COAL",
    "CARGO_TYPE": "Dry Bulk",
    "EMAIL_TYPE": "TC",
    "MIN_SIZE": "2026",
    "MAX_SIZE": "973035",
    "BROKER": "MR. DEEPESH MAJIGAMKAR",
    "DURATION": "25",
    "DEL_PORT": "PORT ARTHUR",
    "REDEL_PORT": "WW",
    "REGION": "CHINA"
  }
}