{
  "text": "Best Regards:\nMR. DEEPESH MAJIGAMKAR\nMob:- + 91 9730358718 (whatsapp) // +91 9156366155\nTeams/Skype:deepeshmajigamkar@hotmail.com\nEmail:\nchartering@varitasnavigation.com\nWebsite:-\nwww.varitasnavigation.com\nFrom:\nChartering *Wheel & Time* <chartering@wheeltime.in>\nSent:\n10 December 2025 13:45\nTo:\nchartering@varitasnavigation.com\nSubject:\nBREAK BULK MOVEMENT FROM KANDLA TO JUBAIL/DAMMAM PORT//\nDear Deepesh\nGood Day!\nWe have a detailed discussion with the customer below is fyi :-\n+++++++++++++++++++++++++++++++++\nCargo Details\nPhotos of the actual cargo to better understand the configuration and plan the loading arrangement.\nIts not yet manufactured, so physical photographs are not available, however complete configuration is given to understand the cargo, find below diagram which will give you the complete idea about cargo.\nPlease confirm whether the pipes are bundled with belts/straps.\nIts heavy pipes with large diameter, bundling not possible, pipes will be in unitized form, single pipes to be handle at a time while loading/offloading/stacking.\nPlease advise if any items include coatings, internal lining, or end caps.\nIts Bare pipes will have varnish coating on internal and external surface. Both ends will have plastic End caps with metallic bevel edge protectors.\nShipment Planning\nSpecific quantity and readiness date for the\nfirst batch\nof cargo.\nAbout 490-500 Pipes / 8500 MT/44000 CBM – for one Supramax Shipment-\nMid Jan’26 1\nst\nshipment\n.\nExpected production completion date and when the factory can hand over the cargo to the port.\nProduction and dispatch will run simultaneously, and each month we are expecting 02 shipment to finish it in next 06 months (about 11-12 Shipment)\nPlease confirm whether the plan of\n2 shipments per month\nis fixed or flexible.\nits almost fixed, little bit flexibility will be there depending on production and dispatch plan\n.\nEstimated delivery location in KSA if you would like us to quote\ncustoms clearance and local delivery\nseparately (as we are also licensed customs brokers and transporters in KSA).\nThe cargo will be delivered 0n FO Jubail basis. Hence customs clearance and local delivery is in client’s scope\n.\nPlease advise if lashing & securing costs should be included in our freight offer.\nYes, sea freight to be offered including LSD\nFor your reference, the bulk carriers we work with have a single-voyage loading capacity of approximately\n50,000–60,000 CBM\n, equating to around\n700 pipes per sailing\n. Once we receive the above information, we will match\nBeing a higher OD 18 mtrs length, traditional bulk carrier hold can accommodate only single stack in hold max up to 9 tiers,  review your working and have pre-stowage plan along with dunnaging/Lashing/securing procedure to understand method of stow and how you arrived 50-60K CBM per shipment\n.\n++++++++++++++++++++++++++++++++++++++++++++\nCargo\n: Steel Bare Line pipes. (Unit length 18 mtrs)\nQty & Configuration\n: As per BOQ given below\nLoad Port\n: Kandla, WCI\nDisport\n: Jubail, KSA (May keep Dammam option also)\nTerm:\nLIFO CQD (Liner in under hook/Free Out CQD)\nLaycan\n: Commencing from End’ January, 2026 @ 2 shipments / month\nNil adcom\nFree period\n: Require 07 working days at berth both ends free of detention.\nTier Restriction\n: 8-9 tiers max.\nCargo configuration\n.\nItem No.\nOD\nOD\nThk\nType of Pipe\nQty mtrs\nPipe Length\nPipe Nos.\nQty in MT\nvolume of pipes\nCBM Ratio per size\nWeight of pipe (MT)\ninch\nmm\nmm\n1\n88\n2235.2\n17.48\nSAWH\n25,280\n18\n1,404\n24,170\n1,26,410.22\n5.23\n17.21\n2\n88\n2235.2\n17.48\nSAWH\n26,190\n18\n1,455\n25,040\n1,30,960.82\n5.23\n17.21\n3\n88\n2235.2\n17.48\nSAWH\n26,725\n18\n1,485\n25,552\n1,33,638.20\n5.23\n17.21\n4\n88\n2235.2\n17.48\nSAWH\n21,764\n18\n1,209\n20,809\n1,08,829.04\n5.23\n17.21\nGrand Total:\n99,958\n5,553\n95,571\n4,99,838.28\n5.23\n5%WT\n🙏\nNamaste\nThanks and Best Regards |\nधन्यवाद एवं शुभकामनाएँ\nNitu Sharma/9158616999\nWheel & Time Shipping Transport Logistics.\n≡ For and on behalf of owners / as agents only ≡\nVatika Business Center, Supreme Business Park, Hiranandani Gardens, Powai,Mumbai - 400 076. INDIA.\nWebsite:\nwww.wheeltime.in",
  "entities": {
    "LAYCAN": "11-12 Shi",
    "CONTACT": "deepeshmajigamkar@hotmail.com",
    "EMAIL": "deepeshmajigamkar@hotmail.com",
    "PHONE": "91 9730358718 ",
    "LOAD_PORT": "Kandla, WCI",
    "CARGO": "STEEL",
    "CARGO_TYPE": "General Cargo",
    "TONNAGE_TYPE": "Bulk Carrier",
    "EMAIL_TYPE": "UNKNOWN",
    "MIN_SIZE": "1209",
    "MAX_SIZE": "973035",
    "BROKER": "MR. DEEPESH MAJIGAMKAR",
    "DEL_PORT": "location in KSA if you would like us to quote",
    "REGION": "ECI"
  }
}