{
  "text": "Thanks and Regards,\nMs. Eleanor Rodriguez\nOperations Executive\nSobha Sapphire Bldg. Office No. 906 Business Bay, P.O. Box 123175, Dubai United Arab Emirates\nTel: (+9714) 434 1628 l Fax: (+9714) 434 1629 l Mobile/Whatsapp: (+97150) 456 9584\nTeams:\n⁠\nTransbulk5\nWeChat: TransbulkOps_Eleanor\nEmail:\noperations@transbulk.ae\n|\ntransblk@eim.ae\nWebsite:\nhttp://www.transbulk.ae\nFrom:\nChrigr <christoship@chri.gr>\nSent:\nWednesday, 26 November 2025 12:34 PM\nTo:\nChrigr <christoship@chri.gr>\nSubject:\nMV DEVBULK ALARA (31,018 DWT / 2011 BLT) OPEN JORF LASFAR 1 - 2ND NOVEMBER ONW (REF:25A63DF)\n26/11/25 10:34 +02:00\nCHRISTOSHIP\nShipbroking S.A. - Since 1974\nMembers of the Hellenic Shipbrokers Association - BIMCO Reg. Nr. 100812\n1974-2024 50 years\n130, Vouliagmenis Avenue, Elliniko 167 77, Greece\nPhone: +30 210-428 2910   Fax: +30 210-428 2362\nEmail:\nchristoship@chri.gr\n- / GEORGE\nFROM OUR CLOSE HOWNERS:\nMV DEVBULK ALARA (31,018 DWT / 2011 BLT) OPEN JORF LASFAR 1 - 2ND NOVEMBER ONW\nPREF TRADE WITHIN ATLANTIC\nVOY OR TCT OK\n- CAN TRY 2/3 LLEGS, REDELY ATLANTIC\n- CAN TRY SHORT PERIOD\nLAST FIVE CARGO : SCRAP(LAST) - CORN - MOP – MOP - LDAN/HDAN IN BAG\nMV DEVBULK ALARA\n31,018 DWT ON 10,02M SSW – TPC: 43,7\nSINGLE DECK DOUBLE HULL, WIDEHATCH\nIMO NUMBER:9449895\nBUILT 2011 – TSUJI HEAVY INDUSTRIES\nMARSHALL ISLANDS FLAG - P&I UK CLUB - ABS CLASS\nGRT 19,999 / NT 10,792\nLOA 178,7M / BEAM 28M / DEPTH 14M / LBP 170M\nGRAIN/BALE: 1,434,952 / 1,363,203 CBFT\nGEARED 4 X 30 MTS CRANES\n5 HO/5 HA (HYDRAULIC FOLDING TYPE)\nREMOTE CONTROL 2 X 12 CBM GRABS (USAGE SUB TO AGREEMENT)\nBWTS+ A60+ ITF + CO2 +AHL FITTED\nDAILY SPEED/CONSUMPTION:\nBALLAST   : ABT 12,50 KNOTS ON ABT 18,50 MT VLSIFO+ 0,1MT LSMGO\nLADEN    : ABT 12,00 KNOTS ON ABT 18,50MT VLSIFO + 0,1MT LSMGO\nPORT:\nIDLE        : ABT 3,0MTS VLSIFO\nGEAR      : ABT 5,6 MTS VLSIFO\nALL DETAILS/FIGURES ARE ABOUT\nBest Regards,\nGeorge Kostas |\nCHRISTOSHIP Shipbroking S.A.\nMob/Whatsapp: +30 6940509872 | Wechat: gk_christoship | Teams:gakostas@gmail.com",
  "entities": {
    "VESSEL": "MV DEVBULK ALARA",
    "DWT": "31,018",
    "PORT": "JORF LASFAR",
    "CONTACT": "operations@transbulk.ae",
    "EMAIL": "operations@transbulk.ae",
    "PHONE": "434 1628 ",
    "OPEN_PORT": "JORF LASFAR",
    "CARGO": "GRAIN",
    "CARGO_TYPE": "Dry Bulk",
    "EMAIL_TYPE": "TONNAGE",
    "MIN_SIZE": "1363",
    "MAX_SIZE": "944989",
    "IMO": "9449895",
    "BROKER": "George Kostas",
    "DEL_PORT": "ATLANTIC"
  }
}