{
  "text": "Best Regards:\nMR. DEEPESH MAJIGAMKAR\nMob:- + 91 9730358718 (whatsapp) // +91 9156366155\nTeams/Skype:deepeshmajigamkar@hotmail.com\nEmail:\nchartering@varitasnavigation.com\nWebsite:-\nwww.varitasnavigation.com\nFrom:\nMary Fatima Duhina <mary@seaspeedmarine.com>\nSent:\n14 January 2026 17:34\nSubject:\nM/V DIAMOND STAR II - 57K DWT/ 2011 BLT OPEN DJIBOUTI 25-31ST JAN, 2026 AGW WP\nDEAR SIR,\nGOOD DAY!\nKINDLY PLS PPS FOR FIRM BIZ FOR THE BELOW VSL FROM OUR CLOSE OWNRS:\n======================================================\nM/V DIAMOND STAR II - 57K DWT/ 2011 BLT OPEN DJIBOUTI 25-31ST JAN, 2026 AGW WP\nPrefer single trip to fareast\nM/V DIAMOND STAR II\nFLAG: PANAMA\nBLT:MARCH, 2011\nSTX (DALIAN) SHIPBUILDING CO., LTD.\nIMO NUMBER: 9449273\nPORT OF REGISTRY : PANAMA\nCLASS : ABS\nSUMMER DWT : 57272.5 MT\nDRAFT : 13.020 M\nTPC :57.3 MT/CM\nLOA / BEAM : 190M / 32.26M\nGT / NT : 33205 / 18891\nGRAIN / BALE: ABT 71967 / 66874\nHO / HA : 5/5, CO2 FITTED.\nCRANES : 4X30MT SWL + GRABS 4X12 CBM\nSPEED /CONSUMPTIONS ( LSIFO / LSMGO)\nFULL SPEED LADEN  ABT    - 12.0 @ 25.50 MT NDAS\nFULL SPEED BALLAST ABT  - 12.0 @ 24.00 MT NDAS\nECO SPEED LADEN ABT      - 11.0 @ 23.00 MT NDAS\nECO SPEED BALLAST ABT   - 11.0 @ 22.00 MT NDAS\nIN PORT - WORKING 5.8MT + 0.2MT  ... IDLE 3.5MT + 0.2MT\n- “ABT” MEANS AN ALLOWANCE OF +/-0.5KN ON SPEED AND 5PCT ON CONSUMPTION\n- SPEED AND CONSUMPTION DESCRIBED ABOVE IS THE AVERAGE FOR FULL CHARTER PERIOD IN TCT INCLUDING VESSEL PERFORMANCE IN BALLAST AND LADEN.\n- THE SPEED AND CONSUMPTION ARE BASED ON CLEAN HULL AND GOOD WEATHER CONDITION MAX BEAUFORT SCALE 4 AND DOUGLAS SEA STATE 3 WITH NO ADVERSE, SEA BUOY TO SEA\nBUOY, EXCLUDING CANALS, NARROW AND RESTRICTED WATERS AND PERIODS WHEN SPEED IS REDUCED DUE TO CHARTERERS\\' ORDERS, REASONS OF SAFETY AND POOR\nVISIBILITY ETC. WHEN BALLASTING /DEBALLASTING ABT 2.00 MT LSMGO FOR THE OPERATION.\n- FOR PERFORMANCE EVALUATION PURPOSES, THE OVERALL PERFORMANCE OF THE VESSEL IS TO BE REVIEWED ON ALL LEGS, LADEN AND BALLAST PASSAGES DURING\nTHE CURRENCY OF THE CHARTER PARTY. ANY SAVING IN CONSUMPTION MUST BE OFFSET AGAINST ANY REDUCTION IN SPEED. ANY SAVING IN TIME MUST BE OFF-SET\nAGAINST EXCESS CONSUMPTION. ANY SAVING IN FUEL OIL MUST BE OFF-SET AGAINST INCREASED MDO CONSUMPTION AND VICE VERSA. BAD WEATHER DAYS NOT TO\nBE TAKEN INTO ACCOUNT.THE SAILING DISTANCE IN BAD WEATHER DAYS CAN BE CALCUATED AS PER THE SPEED/CONSUMPTION DATA IN GOOD WEATHER .\n- VESSEL HAVE LIBERTY TO BURN LSMGO WHEN MANEUVERING, IN/OUT OF PORTS, NAVIGATING IN CONFINED WATERS, CROSSING CANALS, RIVERS, STRAITS AND\nDURING POOR VISIBILITY/ EMERGENCY\n- VESSEL TO HAVE THE LIBERTY OF SLOW-STEAMING AT SEA FOR THE PURPOSES OF BALLAST EXCHANGE, WITHOUT CLAIM, IF REQUIRED.\n- QUALITY OF BUNKERS SUPPLIED BY CHARTERERS TO CONFORM TO LATEST SULPHUR REGULATIONS 2020, MARPOL COMPLIANT OR LATEST (MAX SULPHUR CONTENT 0.5%).\nFUEL OIL – RMG380, (FOR SECA AREA MAX SULPHUR CONTENT 0.1%) DIESEL OIL –DMB (LESS THEN 0.1 %). ISO 8217-2010 SPECS TO BE ALLOWED DURING THE CP.\n- IN SECA AREAS FUEL OIL AND DIESEL SUPPLIED BY CHARTERER\\'S TO ALSO CONFIRM TO LOCAL REGULATORY REQUIREMENTS.\nPLSD TO HEAR!\nBest Regards,\nMary Fatima Duhina\nChartering Executive\nSeaspeed Marine Management LLC\n1104, Mohammed Al Mulla Tower, Al Ittihad Road, P.O.Box 32658, Sharjah, U.A.E.\nTel :\n+971 6 5638938 | Fax : +971 6 5638939\nEmail:\ndry@seaspeedmarine.com\n|\nmary@seaspeedmarine.com\nTeams ID\n:\nhttps://teams.live.com/l/invite/FEAcsGvdoh-MRVgnQQ\nWechat ID & Whatsapp :\n+971 50 860 7046\nWebsite\n:\nwww.seaspeedmarine.com\nAs Brokers Only\nNote:\nSeaspeed Marine Management LLC will be migrating to our new email domain of\nseaspeedmarine.com\nfrom 1\nst\nFeb 2025.\nAll email addresses will change from:\n@cspeed.ae\nto\n@seaspeedmarine.com\n.\nRequest you to kindly update your address book to reflect the same.\nNote:\nSeaspeed Marine Management LLC will be migrating to our new email address,\ndry@seaspeedmarine.com\nfrom 1\nst\nFeb 2025. Request you to kindly update your address book to reflect the same and prevent any loss of communication.",
  "entities": {
    "PORT": "DJIBOUTI",
    "LAYCAN": "25-31ST JAN",
    "CONTACT": "deepeshmajigamkar@hotmail.com",
    "VESSEL": "MV DIAMOND STAR II - 57K DWT",
    "EMAIL": "deepeshmajigamkar@hotmail.com",
    "PHONE": "91 9730358718 ",
    "OPEN_PORT": "DJIBOUTI",
    "DWT": "57272.5",
    "CARGO": "GRAIN",
    "CARGO_TYPE": "Dry Bulk",
    "EMAIL_TYPE": "TONNAGE",
    "MIN_SIZE": "1104",
    "MAX_SIZE": "973035",
    "IMO": "9449273",
    "BROKER": "MR. DEEPESH MAJIGAMKAR"
  }
}