{
  "text": "Best Regards:\nMR. DEEPESH MAJIGAMKAR\nMob:- + 91 9730358718 (whatsapp) // +91 9156366155\nTeams/Skype:deepeshmajigamkar@hotmail.com\nEmail:\nchartering@varitasnavigation.com\nWebsite:-\nwww.varitasnavigation.com\nFrom:\nAllimar Shipbrokers srl <chartering@allimar.it>\nSent:\n02 January 2026 14:53\nTo:\nAllimar Shipbrokers srl <chartering@allimar.it>\nSubject:\nSohar/Dar-es-Salaam - 5244 cbm project cargo\n- 5244 cbm project cargo\n-Sohar/Dar-es-Salaam\n-99 pckgs = 1010 mts = 5244 cbm project cargo non-stackable (p/l available here on demand)\n-10/20 Jan\n-FLT\n-3,75% iac\nALLIMAR SHIPBROKERS s.r.l.\n+39/3356759395\nchartering@allimar.it\nallimar@tiscali.it\n(circulars & positions only)\nallimarship\nwxid_02g3slkt8c8r12",
  "entities": {
    "CONTACT": "deepeshmajigamkar@hotmail.com",
    "EMAIL": "deepeshmajigamkar@hotmail.com",
    "PHONE": "91 9730358718 ",
    "CARGO": "5244 cbm project cargo",
    "CARGO_TYPE": "Project Cargo",
    "EMAIL_TYPE": "VC",
    "MIN_SIZE": "1010",
    "MAX_SIZE": "973035",
    "BROKER": "MR. DEEPESH MAJIGAMKAR"
  }
}