{
  "text": "Best Regards:\nMR. DEEPESH MAJIGAMKAR\nMob:- + 91 9730358718 (whatsapp) // +91 9156366155\nTeams/Skype:deepeshmajigamkar@hotmail.com\nEmail:\nchartering@varitasnavigation.com\nWebsite:-\nwww.varitasnavigation.com\nFrom:\nBulk - Marcons - Marcons Group <bulk@marconsgroup.com>\nSent:\n09 January 2026 15:55\nTo:\nMarcons Bulk Chartering <bulk@marconsgroup.com>\nSubject:\nMV PVT PERIDOT / 57359 DWT / YANTAI, CHINA / 12-14 JAN\n(Pls do add ours mail id :-\nbulk@marconsgroup.com\nin your circulation lists)\nDEAR CHARTERING DESK / MARCONS\nGOOD DAY, HOPE ALL FINE AND WELL\nPLSD TO HEAR FOR FIRM AND RATED BIZ FOR THE BELOW CANDIDATE\nMV PVT PERIDOT (2013) - 57,359MTS /13.2 M\n-- OPEN YANTAI 12-14 JAN\n-- GOA OK / USA OK / WAFR HRA OK / PERIOD OK / 2X20 OK\n-- CAN TRY ANY DIRECTION\nMV PVT PERIDOT\nBUILT: 2013 AT STX DALIAN\nFLAG: PANAMA\nCLASS: DNV.\n57.300 DWT ON 13,0 M SSW\nGRT/NRT: 33.361/19.338\nLOA/BEAM: 190M/32,30M.\nGRAIN/BALE: 71.956 CBM/68.239 CBM.\nGEAR/GRAB: 4*30 TS/ 4*14 CBM EACH.\nHO/HA: 5/5.\nHATCH COVER: HYRAULIC FOLDING TYPE.\n- FULL SPEED : -\nBALLAST : ABOUT 12.5 KNOTS / ABT 22.5 MT VLSFO + ABT 0.10 MT LSMGO LADEN : ABOUT 12 KNOTS / ABT 24 MT VLSFO + ABT 0.10 MT LSMGO\n- ECO SPEED : -\nBALLAST : ABOUT 11.5 KNOTS / ABT 18.5 MT VLSFO + ABT 0.10 MT LSMGO LADEN : ABOUT 11 KNOTS / ABT 20 MT VLSFO + ABT 0.10 MT LSMGO\n- IN PORT:\nIDLE : ABT 3.0 MT VLSFO + ABT 0.10 MT LSMGO WORKING : ABT 4.5 MT VLSFO + ABT 0.10 MT LSMGO\n=ALL DETAILS ABOUT=\nThanks and best regards;\nCapt. Momin        |  Mobile : +919769282905 / +971553685524\n|\nTeams\n:\nbulk@marconsgroup.com\nHarsh Jaiswal       |  Mobile : +918591913284 / +919653330919   |  Teams  :\nh\narshhjjaiwal45@outlook.com\nYaksh Shetty         |  Mobile : +919820709980 / +918511160033  |   Teams  :\nyakshetty2024@gmail.com\nKrishna Ganesh   |  Mobile : +919820703018 / +919542506281   |  Teams  :\nshipbroker1999@gmail.com\nO.B.O\nMarcons Shipmanagement Pvt. Ltd.\n(A Dry Cargo Ship Broking Company)\nAddress : G3/G4, \\'A\\' Wing, Navbharat Estates,\nZakaria Bunder Road, Sewri (West),\nMumbai - 400015, India\nMail / Teams :\nbulk@marconsgroup.com\nWebsite         :\nwww.marconsgroup.com",
  "entities": {
    "VESSEL": "MV PVT PERIDOT",
    "DWT": "57359",
    "PORT": "YANTAI",
    "LAYCAN": "12-14 JAN",
    "CONTACT": "deepeshmajigamkar@hotmail.com",
    "EMAIL": "deepeshmajigamkar@hotmail.com",
    "PHONE": "91 9730358718 ",
    "OPEN_PORT": "YANTAI",
    "CARGO": "GRAIN",
    "CARGO_TYPE": "Dry Bulk",
    "EMAIL_TYPE": "UNKNOWN",
    "MIN_SIZE": "1999",
    "MAX_SIZE": "973035",
    "OPEN_DATE": "12 JAN",
    "CLOSE_DATE": "14 JAN",
    "BROKER": "MR. DEEPESH MAJIGAMKAR",
    "REGION": "CHINA"
  }
}