{
  "text": "Best Regards:\nMR. DEEPESH MAJIGAMKAR\nMob:- + 91 9730358718 (whatsapp) // +91 9156366155\nTeams/Skype:deepeshmajigamkar@hotmail.com\nEmail:\nchartering@varitasnavigation.com\nWebsite:-\nwww.varitasnavigation.com\nFrom:\nAkshay Kutwal <akshay.k@integr8fuels.com>\nSent:\n13 January 2026 17:01\nSubject:\nLet’s Catch Up in London – International Energy Week 2026\nHi All,\nWith International Energy Week coming up in London (10–12 February 2026), I’d love to catch up with industry colleagues who will be in town.\nPlease let me know your availability for a casual meet and greet—a great chance to reconnect, share a few thoughts, and kick off the week together before the busy schedule begins.\nHope you can make it, and I look forward to seeing you in London!\nKind regards\nAkshay Kutwal\nBunker Trader\nMob:       +44 7738 982 807\nSkype:     live:.cid.631159075d2bb837\nDesk:\nakshay.k@integr8fuels.com\nWeb:\nwww.integr8fuels.com\nIntegr8 Europe Ltd\n6\nth\nFloor, The Zig Zag Building\n70 Victoria Street\nLondon SW1E6SQ",
  "entities": {
    "CONTACT": "deepeshmajigamkar@hotmail.com",
    "EMAIL": "deepeshmajigamkar@hotmail.com",
    "PHONE": "91 9730358718 ",
    "EMAIL_TYPE": "UNKNOWN",
    "MIN_SIZE": "2026",
    "MAX_SIZE": "973035",
    "BROKER": "MR. DEEPESH MAJIGAMKAR"
  }
}