{
  "text": "Thanks and Regards,\nShabu O.V. FICS, CMILT,MNI, FSCM\nManaging Director\nSobha Sapphire Bldg. Office No. 906 Business Bay 123175, Dubai, United Arab Emirates\nTel: (+9714) 434 1628 l Fax: (+9714) 434 1629 l\nMob: +97150 559 3926\nEmail:\novshabu@transbulk.ae\nl Skype: Transbulk1\nWebsite:\nhttps://transbulk.ae\nFrom:\nArrow Pacific Handy <mktg.pacific.handy@arrowship.com>\nSent:\nWednesday, 26 November 2025 11:50 AM\nTo:\nUndisclosed recipients:\nSubject:\n-MV SEA SPIRIT -EX-LAS PALMAS (PENGLAI JINGLU 63 / 21) -OPEN BIN QASIM, PAKISTAN O/A 7-10 2025\n++FRESH++\n-MV SEA SPIRIT -EX-LAS PALMAS (PENGLAI JINGLU 63 / 21)\n-OPEN BIN QASIM, PAKISTAN O/A 7-10 2025\nPREFER BH/TRY ANY\n-Last 5 cargo’s: coal/Slag/M.ore/coal /bagged cement\n-\nBROB – 873 MT VLSFO/206 MT LSMGO\nBUILT 2021 – PENGLAI ZHONGBAI JINGLU SHIP INDUSTRY\nPANAMA FLAG - CLASS BV\nTIER 3 NOX / FUEL SAVING DEVICES\nABT 63.500 DWT ON ABT 13.50 MTRS SSW (SCANTLING)\nLOA 199.90 MTRS / BEAM 32.26 MTRS\nGRAIN CAP ABT 78.325 CBM - 5/5 HO/HA - CO2 FITTED IN CARGO HOLDS\nA60 BULKHEAD FITTED\nGRAB FITTED PEINER SMAG 12 CBM\nSPEED / CONS (INCLUDING A/E)\nBALLAST : ABT 14.00 KNOTS ON ABT 24.00 MTS VLSIFO 380 CST + ABT 0,1 MTS LSMGO\nLADEN : ABT 13.00 KNOTS ON ABT 24.00 MTS VLSIFO 380 CST + ABT 0,1 MTS LSMGO\nECO SPEED / CONS (INCLUDING A/E)\nBALLAST : ABT 12.00 KNOTS ON ABT 16.00 MTS VLSIFO 380 CST + ABT 0,1 MTS LSMGO\nLADEN : ABT 11.00 KNOTS ON ABT 16.00 MTS VLSIFO 380 CST + ABT 0,1 MTS LSMGO\nPORT/ANCHORAGE CONSUMPTION:\nIDLE: ABT 3.0 MT VLSIFO 380 CST, DAILY\nWORKING: ABT 6.5 MT VLSIFO CST, DAILY.\nABT\" MEANS +/-5% ON SPEED & CONSUMPTION, BOTH TOLERANCE TO APPLY.\nADA\n===========================================================\nARROW PACIFIC TEAM:\nALLEN\n+852 92421696\nDJ\n+65 96875634\nHONEY\n+65 81298899\nIJ\n+81 8010568875\nJANSON\n+65 96499508\nJONATHAN\n+65 83389078\nJUVENTINO\n+65 80278660\nMATT\n+65 6496 7702\nREO\n+81 8078529858\nSTEVEN\n+65 96256508\nTANNAZ\n+65 88708600\nTHOMAS\n+65 92729865",
  "entities": {
    "VESSEL": "MV SEA SPIRIT",
    "DWT": "63500",
    "PORT": "BIN QASIM",
    "CONTACT": "ovshabu@transbulk.ae",
    "EMAIL_TYPE": "TONNAGE",
    "OPEN_PORT": "Bin Qasim",
    "OPEN_DATE": "2025-12-07",
    "CLOSE_DATE": "2025-12-10",
    "TONNAGE_TYPE": "Bulk Carrier",
    "BROKER": "Shabu O.V.",
    "EMAIL": "ovshabu@transbulk.ae",
    "PHONE": "+97150 559 3926",
    "CARGO": "COAL",
    "CARGO_TYPE": "Dry Bulk",
    "MIN_SIZE": "1628",
    "MAX_SIZE": "968756",
    "REGION": "ECI"
  }
}