{
  "text": "Best Regards:\nMR. DEEPESH MAJIGAMKAR\nMob:- + 91 9730358718 (whatsapp) // +91 9156366155\nTeams/Skype:deepeshmajigamkar@hotmail.com\nEmail:\nchartering@varitasnavigation.com\nWebsite:-\nwww.varitasnavigation.com\nFrom:\ndhha@snsshipping.co.kr <dhha@snsshipping.co.kr>\nSent:\n14 January 2026 13:46\nTo:\ndhha@snsshipping.co.kr\nSubject:\nOPEN FAREAST / S.CHINA / USWC / WCCA\nHPC DREAM\n28.0 K\nQINZHOU\n24-Jan\nHPC VISION\n28.0 K\nYANGPU\n23-Jan\nCLIPPER TARPON\n30.4 K\nYANGPU\n14-Jan\nSUNNY HONOR\n32.0 K\nSHIDAO\n26-Jan\nHPC PHOENIX\n32.0 K\nFANGCHENG\n01-Feb\nOHBS, AUSSIE CLEAN\nHAI PHUONG STAR\n32.1 K\nKAOHSIUNG\n22-Jan\nMISSY ENTERPRISE\n32.7 K\nTOMAKOMAI\n23-Jan\nSARE COURSE\n33.1 K\nXIAMEN\n27-Jan\nHL COURAGE\n34.1 K\nCJK\n15-Jan\nCIS OK\n21 GLORY\n37.2 K\nQINZHOU\n19-Jan\nSUMATRA\n38.9 K\nZHENJIANG\n15-Jan\nRUBINA\n39.9 K\nQINZHOU\n16-Jan\nNORSE INNOSHIMA\n40.0 K\nLANSHAN\n18-Jan\nNBR HONOR\n53.6 K\nCAOFEDIAN\n17-Jan\n2X25T/DECK/HATCH/GOA OK\nPELITA MUSTIKAWATI\n55.7 K\nRIZHAO\n24-Jan\n2X25T OK,  NO AUSSIE,  PG/JAPAN RANGE, 3 M PERIOD OK\nAEGIR SELMER\n55.8 K\nCJK\n17-Jan\nHPC ATLANTIC\n56.0 K\nN.CHINA\n13-Feb\nKRISTINA\n58.1 K\nTIANJIN\n25-Jan\nWESTERN SANTIAGO\n62.6 K\nKWANGYANG\n21-Jan\nSCORPIO CONFIDENCE\n63.2 K\nQINGDAO\n19-Jan\nTIGER HEBEI\n63.4 K\nKWANGYANG\n23-Jan\nMILA\n63.5 K\nDAFENG\n25-Jan\nBT TREVIA\n63.5 K\nCJK\n26-Jan\n2X25T/DECK/HATCH OK\nHG BARCELONA\n63.6 K\nCJK\n14-Jan\nTSL ROSEMARY\n33.1 K\nUSWC\n30-Jan\nKEN BOSS\n36.4 K\nPUERTO QUETZAL\n25-Jan\nARIES HONOR\n63.5 K\nPUERTO QUETZAL\n05-Feb\n2X25T/DECK/HATCH/GOA/W.AFRICA HRA OK\n“\nPlease leave message in Teams/Wechat/Whatsapp for quick answer\n“\nDH, Ha ( Ha, dong-hoon )\nSNS Shipping\nTEL : 82-2-6239-5600\nFAX : 82-2-6239-5601\nMobile : 82-10-5327-4011\nEmail :\ndhha@snsshipping.co.kr\nTeams :\nhttps://teams.live.com/l/invite/FEA8O0sR57_LFWPGAM\nWechat : wxid_gadoh6pwo37z22\nWhatsapp : 82-10-5327-4011",
  "entities": {
    "PORT": "FAREAST",
    "CONTACT": "deepeshmajigamkar@hotmail.com",
    "EMAIL": "deepeshmajigamkar@hotmail.com",
    "PHONE": "91 9730358718 ",
    "OPEN_PORT": "FAREAST",
    "EMAIL_TYPE": "TONNAGE",
    "MIN_SIZE": "2026",
    "MAX_SIZE": "973035",
    "BROKER": "MR. DEEPESH MAJIGAMKAR",
    "REGION": "CHINA"
  }
}